hittade_client/__init__.py
hittade_client/client.py
hittade_client/exceptions.py
hittade_client/models.py
hittade_client/py.typed
hittade_client-0.1.2.dist-info/METADATA
hittade_client-0.1.2.dist-info/WHEEL
hittade_client-0.1.2.dist-info/licenses/LICENSE
hittade_client-0.1.2.dist-info/RECORD
